{
  "name": "hitbtc2",
  "parent": "null",
  "children": [
    {
      "name": "plus",
      "parent": "hitbtc2",
      "children": [
        {
          "name": "get",
          "parent": "plus",
          "children": [
            {
              "name": "orderbook",
              "parent": "get"
            },
            {
              "name": "ticker",
              "parent": "get"
            },
            {
              "name": "trade",
              "parent": "get"
            }
          ]
        }
      ]
    },
    {
      "name": "public",
      "parent": "hitbtc2",
      "children": [
        {
          "name": "get",
          "parent": "public",
          "children": [
            {
              "name": "historydata",
              "parent": "get"
            },
            {
              "name": "orderbook",
              "parent": "get"
            },
            {
              "name": "ticker",
              "parent": "get"
            },
            {
              "name": "trades",
              "parent": "get"
            }
          ]
        }
      ]
    },
    {
      "name": "private",
      "parent": "hitbtc2",
      "children": [
        {
          "name": "post",
          "parent": "private",
          "children": [
            {
              "name": "BuyIcebergOrder",
              "parent": "post"
            },
            {
              "name": "BuyOrder",
              "parent": "post"
            },
            {
              "name": "BuyOrder2",
              "parent": "post"
            },
            {
              "name": "BuyStopOrder",
              "parent": "post"
            },
            {
              "name": "CancelIcebergOrder",
              "parent": "post"
            },
            {
              "name": "CancelOrder",
              "parent": "post"
            },
            {
              "name": "CancelStopOrder",
              "parent": "post"
            },
            {
              "name": "GetAccountInfo",
              "parent": "post"
            },
            {
              "name": "getArchivedOrder",
              "parent": "post"
            },
            {
              "name": "getArchivedOrders",
              "parent": "post"
            },
            {
              "name": "GetDeposits",
              "parent": "post"
            },
            {
              "name": "GetIcebergOrder",
              "parent": "post"
            },
            {
              "name": "GetIcebergOrders",
              "parent": "post"
            },
            {
              "name": "GetMarketDepth",
              "parent": "post"
            },
            {
              "name": "GetMarketDepth2",
              "parent": "post"
            },
            {
              "name": "GetOrder",
              "parent": "post"
            },
            {
              "name": "GetOrders",
              "parent": "post"
            },
            {
              "name": "GetStopOrder",
              "parent": "post"
            },
            {
              "name": "GetStopOrders",
              "parent": "post"
            },
            {
              "name": "GetTransactions",
              "parent": "post"
            },
            {
              "name": "GetWithdrawal",
              "parent": "post"
            },
            {
              "name": "GetWithdrawals",
              "parent": "post"
            },
            {
              "name": "RequestWithdrawal",
              "parent": "post"
            },
            {
              "name": "SellIcebergOrder",
              "parent": "post"
            },
            {
              "name": "SellOrder",
              "parent": "post"
            },
            {
              "name": "SellOrder2",
              "parent": "post"
            },
            {
              "name": "SellStopOrder",
              "parent": "post"
            }
          ]
        }
      ]
    }
  ]
}